[
    {
        "episode": 10,
        "q1_loss": 2.5621857564896344,
        "q2_loss": 8.007735409215092,
        "policy_loss": -3.1241156442090867,
        "alpha_loss": -0.10773113363193261,
        "total_reward": -215.9166120249912,
        "touch": 0,
        "won": 0,
        "lost": 0,
        "total_steps": 1915,
        "grad_updates": 320
    },
    {
        "episode": 20,
        "q1_loss": 2.1958737791050225,
        "q2_loss": 8.050030873157084,
        "policy_loss": -3.0757352276705205,
        "alpha_loss": -0.2159478567203223,
        "total_reward": -105.29506371255736,
        "touch": 1,
        "won": 1,
        "lost": 0,
        "total_steps": 3380,
        "grad_updates": 640
    },
    {
        "episode": 30,
        "q1_loss": 1.8764193610598643,
        "q2_loss": 7.919872164602081,
        "policy_loss": -3.0237891315792997,
        "alpha_loss": -0.3240129423723677,
        "total_reward": -230.0229816459753,
        "touch": 0,
        "won": 0,
        "lost": 0,
        "total_steps": 5116,
        "grad_updates": 960
    },
    {
        "episode": 40,
        "q1_loss": 1.5870737482327968,
        "q2_loss": 7.529776773322373,
        "policy_loss": -2.981394304102287,
        "alpha_loss": -0.43193592234224526,
        "total_reward": -173.13832491724162,
        "touch": 0,
        "won": 0,
        "lost": 0,
        "total_steps": 7003,
        "grad_updates": 1280
    },
    {
        "episode": 50,
        "q1_loss": 1.376322837397456,
        "q2_loss": 7.164533757045865,
        "policy_loss": -2.939970594607294,
        "alpha_loss": -0.5399355195514,
        "total_reward": -131.17832836970305,
        "touch": 1,
        "won": 0,
        "lost": 0,
        "total_steps": 8487,
        "grad_updates": 1600
    },
    {
        "episode": 60,
        "q1_loss": 1.225424421361337,
        "q2_loss": 6.895712638832629,
        "policy_loss": -2.893570875842124,
        "alpha_loss": -0.6478141660534372,
        "total_reward": -179.4326401271468,
        "touch": 0,
        "won": 0,
        "lost": 0,
        "total_steps": 10119,
        "grad_updates": 1920
    },
    {
        "episode": 70,
        "q1_loss": 1.1250316906653877,
        "q2_loss": 6.676984259113669,
        "policy_loss": -2.8472642811015247,
        "alpha_loss": -0.7556746217857965,
        "total_reward": -205.14072379752002,
        "touch": 0,
        "won": 0,
        "lost": 0,
        "total_steps": 11970,
        "grad_updates": 2240
    },
    {
        "episode": 80,
        "q1_loss": 1.0750803116185126,
        "q2_loss": 6.487748566409573,
        "policy_loss": -2.8033566999947652,
        "alpha_loss": -0.8634331268290453,
        "total_reward": -54.573016290330855,
        "touch": 1,
        "won": 0,
        "lost": 0,
        "total_steps": 13774,
        "grad_updates": 2560
    },
    {
        "episode": 90,
        "q1_loss": 1.046253999353697,
        "q2_loss": 6.3859159162888925,
        "policy_loss": -2.7597044591067568,
        "alpha_loss": -0.9712685525445826,
        "total_reward": -38.67942379830412,
        "touch": 1,
        "won": 0,
        "lost": 1,
        "total_steps": 15281,
        "grad_updates": 2880
    },
    {
        "episode": 100,
        "q1_loss": 1.0233176222117617,
        "q2_loss": 6.303875595368445,
        "policy_loss": -2.7183739055879412,
        "alpha_loss": -1.0789841699253337,
        "total_reward": -47.96743387141519,
        "touch": 1,
        "won": 1,
        "lost": 0,
        "total_steps": 17150,
        "grad_updates": 3200
    },
    {
        "episode": 10,
        "q1_loss": 2.859534998703748,
        "q2_loss": 7.940402586013079,
        "policy_loss": -3.146283834986389,
        "alpha_loss": -0.10719660479880985,
        "total_reward": -16.431368859005367,
        "touch": 0,
        "won": 0,
        "lost": 1,
        "total_steps": 1774,
        "grad_updates": 320
    },
    {
        "episode": 20,
        "q1_loss": 2.1232649590820074,
        "q2_loss": 7.487098563089967,
        "policy_loss": -3.1533609109930696,
        "alpha_loss": -0.21518509616762457,
        "total_reward": -17.979745236211087,
        "touch": 0,
        "won": 0,
        "lost": 1,
        "total_steps": 3614,
        "grad_updates": 640
    },
    {
        "episode": 30,
        "q1_loss": 1.7756306835760673,
        "q2_loss": 7.354680339992046,
        "policy_loss": -3.132601008253793,
        "alpha_loss": -0.3231048952518904,
        "total_reward": -104.3044846895082,
        "touch": 0,
        "won": 0,
        "lost": 0,
        "total_steps": 5039,
        "grad_updates": 960
    },
    {
        "episode": 40,
        "q1_loss": 1.5717619318282232,
        "q2_loss": 7.129883747920394,
        "policy_loss": -3.1018114933278413,
        "alpha_loss": -0.4308845811787251,
        "total_reward": -27.786361926212003,
        "touch": 0,
        "won": 0,
        "lost": 1,
        "total_steps": 6515,
        "grad_updates": 1280
    },
    {
        "episode": 50,
        "q1_loss": 1.3861838993150741,
        "q2_loss": 6.879270365983248,
        "policy_loss": -3.057343258522451,
        "alpha_loss": -0.5385336509930494,
        "total_reward": -94.3977004586538,
        "touch": 0,
        "won": 0,
        "lost": 0,
        "total_steps": 8148,
        "grad_updates": 1600
    },
    {
        "episode": 60,
        "q1_loss": 1.275317265993605,
        "q2_loss": 6.653480311607321,
        "policy_loss": -3.0169725789067647,
        "alpha_loss": -0.6461442038903139,
        "total_reward": -34.35673959946598,
        "touch": 0,
        "won": 0,
        "lost": 1,
        "total_steps": 9829,
        "grad_updates": 1920
    },
    {
        "episode": 70,
        "q1_loss": 1.1959256241630232,
        "q2_loss": 6.482454817103488,
        "policy_loss": -2.978067089590643,
        "alpha_loss": -0.7538027947387101,
        "total_reward": -54.72170179568863,
        "touch": 1,
        "won": 0,
        "lost": 0,
        "total_steps": 11619,
        "grad_updates": 2240
    },
    {
        "episode": 80,
        "q1_loss": 1.1126948645920494,
        "q2_loss": 6.319868345512077,
        "policy_loss": -2.9395588002866133,
        "alpha_loss": -0.8614343563925104,
        "total_reward": -22.433996484951237,
        "touch": 0,
        "won": 0,
        "lost": 1,
        "total_steps": 13575,
        "grad_updates": 2560
    },
    {
        "episode": 90,
        "q1_loss": 1.0637569821646644,
        "q2_loss": 6.199755446985364,
        "policy_loss": -2.8996848597087794,
        "alpha_loss": -0.9689679454094504,
        "total_reward": -37.22599693995762,
        "touch": 1,
        "won": 0,
        "lost": 0,
        "total_steps": 15204,
        "grad_updates": 2880
    },
    {
        "episode": 100,
        "q1_loss": 1.0313545317016541,
        "q2_loss": 6.100152312070131,
        "policy_loss": -2.859026392083615,
        "alpha_loss": -1.0765106287890376,
        "total_reward": -17.87851791203243,
        "touch": 0,
        "won": 0,
        "lost": 1,
        "total_steps": 16530,
        "grad_updates": 3200
    },
    {
        "episode": 10,
        "q1_loss": 2.9603676784783604,
        "q2_loss": 8.763973309844733,
        "policy_loss": -1.7480871400795877,
        "alpha_loss": -0.10780567782621801,
        "total_reward": -112.87361801340992,
        "touch": 0,
        "won": 0,
        "lost": 0,
        "total_steps": 1963,
        "grad_updates": 320
    },
    {
        "episode": 20,
        "q1_loss": 2.236595410108566,
        "q2_loss": 7.882670992612839,
        "policy_loss": -1.7602738504763693,
        "alpha_loss": -0.21614861143598318,
        "total_reward": -75.18246152053948,
        "touch": 0,
        "won": 0,
        "lost": 0,
        "total_steps": 3580,
        "grad_updates": 640
    },
    {
        "episode": 30,
        "q1_loss": 1.9008049375067155,
        "q2_loss": 7.507177968819936,
        "policy_loss": -1.7336238509354491,
        "alpha_loss": -0.32421992436569175,
        "total_reward": -22.434984033640646,
        "touch": 0,
        "won": 0,
        "lost": 1,
        "total_steps": 5036,
        "grad_updates": 960
    },
    {
        "episode": 40,
        "q1_loss": 1.7232121294829994,
        "q2_loss": 7.3021427659317855,
        "policy_loss": -1.7065769811859355,
        "alpha_loss": -0.4321808382162544,
        "total_reward": -18.597324543749018,
        "touch": 1,
        "won": 0,
        "lost": 1,
        "total_steps": 6396,
        "grad_updates": 1280
    },
    {
        "episode": 10,
        "q1_loss": 4.178435030207038,
        "q2_loss": 13.574551489949226,
        "policy_loss": -3.276314643933438,
        "alpha_loss": -0.10811400777911331,
        "total_reward": -38.583336877093984,
        "touch": 1,
        "won": 0,
        "lost": 1,
        "total_steps": 1476,
        "grad_updates": 320
    },
    {
        "episode": 10,
        "q1_loss": 3.4634405905380845,
        "q2_loss": 10.820184673368932,
        "policy_loss": -2.417281351611018,
        "alpha_loss": -0.10778392086795066,
        "total_reward": -180.4370532506571,
        "touch": 0,
        "won": 0,
        "lost": 0,
        "total_steps": 1542,
        "grad_updates": 320
    },
    {
        "episode": 20,
        "q1_loss": 2.564493081718683,
        "q2_loss": 9.922172833979129,
        "policy_loss": -2.520707566477358,
        "alpha_loss": -0.2161375193114509,
        "total_reward": -169.12904104006594,
        "touch": 0,
        "won": 0,
        "lost": 0,
        "total_steps": 3152,
        "grad_updates": 640
    },
    {
        "episode": 30,
        "q1_loss": 2.051675647373001,
        "q2_loss": 9.073632550487917,
        "policy_loss": -2.5404205954323213,
        "alpha_loss": -0.32443993207707533,
        "total_reward": -208.90455534924942,
        "touch": 0,
        "won": 0,
        "lost": 0,
        "total_steps": 4611,
        "grad_updates": 960
    },
    {
        "episode": 40,
        "q1_loss": 1.7863100636866875,
        "q2_loss": 8.554508949071169,
        "policy_loss": -2.543156665470451,
        "alpha_loss": -0.43251428714502255,
        "total_reward": -176.10567677768148,
        "touch": 0,
        "won": 0,
        "lost": 0,
        "total_steps": 6991,
        "grad_updates": 1280
    },
    {
        "episode": 50,
        "q1_loss": 1.567141805952415,
        "q2_loss": 8.059667816311121,
        "policy_loss": -2.5345869394391776,
        "alpha_loss": -0.5404652745166095,
        "total_reward": -316.25222552614713,
        "touch": 0,
        "won": 0,
        "lost": 0,
        "total_steps": 9269,
        "grad_updates": 1600
    },
    {
        "episode": 60,
        "q1_loss": 1.384987033616441,
        "q2_loss": 7.604807481169701,
        "policy_loss": -2.522197095863521,
        "alpha_loss": -0.6484141351562963,
        "total_reward": -65.53640295040182,
        "touch": 1,
        "won": 0,
        "lost": 0,
        "total_steps": 11769,
        "grad_updates": 1920
    },
    {
        "episode": 70,
        "q1_loss": 1.2759720621297934,
        "q2_loss": 7.2508442489164215,
        "policy_loss": -2.50346914577697,
        "alpha_loss": -0.7562798766606388,
        "total_reward": -251.06372476244763,
        "touch": 0,
        "won": 0,
        "lost": 0,
        "total_steps": 13683,
        "grad_updates": 2240
    },
    {
        "episode": 80,
        "q1_loss": 1.1971930922591127,
        "q2_loss": 6.944277545716614,
        "policy_loss": -2.478481589490548,
        "alpha_loss": -0.864043295283409,
        "total_reward": -216.07120497495615,
        "touch": 0,
        "won": 0,
        "lost": 0,
        "total_steps": 15432,
        "grad_updates": 2560
    },
    {
        "episode": 10,
        "q1_loss": 3.188923640176654,
        "q2_loss": 9.397953310608864,
        "policy_loss": -1.8481041202321649,
        "alpha_loss": -0.10758073116430751,
        "total_reward": -96.26825433057601,
        "touch": 1,
        "won": 0,
        "lost": 0,
        "total_steps": 1711,
        "grad_updates": 320
    },
    {
        "episode": 20,
        "q1_loss": 2.1406148882117124,
        "q2_loss": 8.346975847706199,
        "policy_loss": -1.895657033380121,
        "alpha_loss": -0.2159666349914005,
        "total_reward": -229.17378435438616,
        "touch": 0,
        "won": 0,
        "lost": 0,
        "total_steps": 3456,
        "grad_updates": 640
    },
    {
        "episode": 30,
        "q1_loss": 1.6103956419353684,
        "q2_loss": 7.4131549996634325,
        "policy_loss": -1.8854255457098286,
        "alpha_loss": -0.32415017751281994,
        "total_reward": -152.68005242246593,
        "touch": 0,
        "won": 0,
        "lost": 0,
        "total_steps": 5399,
        "grad_updates": 960
    },
    {
        "episode": 40,
        "q1_loss": 1.3041007924359291,
        "q2_loss": 6.7683759916573765,
        "policy_loss": -1.8731364275794475,
        "alpha_loss": -0.43224782877546203,
        "total_reward": -51.96968534306534,
        "touch": 1,
        "won": 0,
        "lost": 0,
        "total_steps": 7713,
        "grad_updates": 1280
    },
    {
        "episode": 50,
        "q1_loss": 1.1134194308705627,
        "q2_loss": 6.303069006949663,
        "policy_loss": -1.855869423262775,
        "alpha_loss": -0.5402587491194936,
        "total_reward": -260.0328628340614,
        "touch": 0,
        "won": 0,
        "lost": 0,
        "total_steps": 10074,
        "grad_updates": 1600
    },
    {
        "episode": 60,
        "q1_loss": 1.006997601784921,
        "q2_loss": 6.001739809041222,
        "policy_loss": -1.8350714166027804,
        "alpha_loss": -0.6482022610737659,
        "total_reward": -231.12090874601927,
        "touch": 0,
        "won": 0,
        "lost": 0,
        "total_steps": 12427,
        "grad_updates": 1920
    },
    {
        "episode": 70,
        "q1_loss": 0.9494560011030574,
        "q2_loss": 5.7918201260268685,
        "policy_loss": -1.809781965480319,
        "alpha_loss": -0.7560814438065271,
        "total_reward": -200.35450544994924,
        "touch": 0,
        "won": 0,
        "lost": 0,
        "total_steps": 14721,
        "grad_updates": 2240
    },
    {
        "episode": 80,
        "q1_loss": 0.8968819256959251,
        "q2_loss": 5.591613908205181,
        "policy_loss": -1.778643211047165,
        "alpha_loss": -0.8638995812690837,
        "total_reward": -202.67372399379042,
        "touch": 0,
        "won": 0,
        "lost": 0,
        "total_steps": 15924,
        "grad_updates": 2560
    },
    {
        "episode": 90,
        "q1_loss": 0.8445828182752141,
        "q2_loss": 5.410402755770418,
        "policy_loss": -1.7472924252144164,
        "alpha_loss": -0.9715807807484452,
        "total_reward": -117.48238763266276,
        "touch": 1,
        "won": 0,
        "lost": 1,
        "total_steps": 17673,
        "grad_updates": 2880
    },
    {
        "episode": 100,
        "q1_loss": 0.8068062086380087,
        "q2_loss": 5.252765840776265,
        "policy_loss": -1.712421490829438,
        "alpha_loss": -1.079271025877224,
        "total_reward": -125.8393301355719,
        "touch": 1,
        "won": 0,
        "lost": 0,
        "total_steps": 19625,
        "grad_updates": 3200
    },
    {
        "episode": 10,
        "q1_loss": 2.6089050037786365,
        "q2_loss": 7.916895121335983,
        "policy_loss": -3.766194546967745,
        "alpha_loss": -0.1079445263640082,
        "total_reward": -184.25115078278998,
        "touch": 1,
        "won": 0,
        "lost": 0,
        "total_steps": 1737,
        "grad_updates": 320
    },
    {
        "episode": 20,
        "q1_loss": 2.2713507803156974,
        "q2_loss": 8.605956769362091,
        "policy_loss": -3.7162649128586054,
        "alpha_loss": -0.2163312812703225,
        "total_reward": -284.49262951102105,
        "touch": 0,
        "won": 0,
        "lost": 0,
        "total_steps": 3492,
        "grad_updates": 640
    },
    {
        "episode": 30,
        "q1_loss": 1.868362992691497,
        "q2_loss": 8.164676030973594,
        "policy_loss": -3.647229234625896,
        "alpha_loss": -0.32451764925038634,
        "total_reward": -2.9386461911704593,
        "touch": 0,
        "won": 1,
        "lost": 0,
        "total_steps": 5174,
        "grad_updates": 960
    },
    {
        "episode": 40,
        "q1_loss": 1.6773077178979292,
        "q2_loss": 7.926129481941461,
        "policy_loss": -3.5760048585012556,
        "alpha_loss": -0.43255278656233714,
        "total_reward": -99.14948586150628,
        "touch": 1,
        "won": 0,
        "lost": 0,
        "total_steps": 7317,
        "grad_updates": 1280
    },
    {
        "episode": 50,
        "q1_loss": 1.5860193388350308,
        "q2_loss": 7.719512119293213,
        "policy_loss": -3.4923551553487777,
        "alpha_loss": -0.5405120959652413,
        "total_reward": -200.34789216081566,
        "touch": 0,
        "won": 0,
        "lost": 0,
        "total_steps": 9628,
        "grad_updates": 1600
    },
    {
        "episode": 60,
        "q1_loss": 1.4902168763491015,
        "q2_loss": 7.480023717383544,
        "policy_loss": -3.414548537756006,
        "alpha_loss": -0.6484632443448693,
        "total_reward": -174.61857441299614,
        "touch": 0,
        "won": 0,
        "lost": 0,
        "total_steps": 11714,
        "grad_updates": 1920
    },
    {
        "episode": 70,
        "q1_loss": 1.4663111619119134,
        "q2_loss": 7.3080741690737865,
        "policy_loss": -3.3476523819778645,
        "alpha_loss": -0.7563626560620573,
        "total_reward": -89.66207459244426,
        "touch": 1,
        "won": 0,
        "lost": 0,
        "total_steps": 13523,
        "grad_updates": 2240
    },
    {
        "episode": 80,
        "q1_loss": 1.4350398215930908,
        "q2_loss": 7.20243351040408,
        "policy_loss": -3.2950771119445563,
        "alpha_loss": -0.8642774037410164,
        "total_reward": -94.06189205038325,
        "touch": 1,
        "won": 0,
        "lost": 0,
        "total_steps": 15036,
        "grad_updates": 2560
    },
    {
        "episode": 90,
        "q1_loss": 1.3898229443468153,
        "q2_loss": 7.080395664274692,
        "policy_loss": -3.2458585878213246,
        "alpha_loss": -0.9721440734009472,
        "total_reward": -173.00449787808705,
        "touch": 0,
        "won": 0,
        "lost": 0,
        "total_steps": 16495,
        "grad_updates": 2880
    },
    {
        "episode": 100,
        "q1_loss": 1.3458839481230824,
        "q2_loss": 6.932411627098918,
        "policy_loss": -3.200080993697047,
        "alpha_loss": -1.0799703160933132,
        "total_reward": -45.941559315085954,
        "touch": 1,
        "won": 0,
        "lost": 1,
        "total_steps": 18368,
        "grad_updates": 3200
    },
    {
        "episode": 10,
        "q1_loss": 1.4263496305793524,
        "q2_loss": 19.662850710749627,
        "policy_loss": 1.161845628451556,
        "alpha_loss": 0.0,
        "total_reward": -26.02034297331948,
        "touch": 0,
        "won": 0,
        "lost": 1,
        "total_steps": 467,
        "grad_updates": 320
    },
    {
        "episode": 20,
        "q1_loss": 1.1329420308582485,
        "q2_loss": 29.59621195346117,
        "policy_loss": 1.7346906331833452,
        "alpha_loss": 0.0,
        "total_reward": -23.04468953724118,
        "touch": 0,
        "won": 0,
        "lost": 1,
        "total_steps": 770,
        "grad_updates": 640
    },
    {
        "episode": 30,
        "q1_loss": 1.1065583466552198,
        "q2_loss": 37.801937422156335,
        "policy_loss": 2.0899957542307677,
        "alpha_loss": 0.0,
        "total_reward": -107.37250833920693,
        "touch": 1,
        "won": 0,
        "lost": 1,
        "total_steps": 1224,
        "grad_updates": 960
    },
    {
        "episode": 40,
        "q1_loss": 1.183793534594588,
        "q2_loss": 44.320905012637375,
        "policy_loss": 2.3397939001908528,
        "alpha_loss": 0.0,
        "total_reward": 4.195300618327591,
        "touch": 1,
        "won": 1,
        "lost": 0,
        "total_steps": 1652,
        "grad_updates": 1280
    },
    {
        "episode": 50,
        "q1_loss": 1.241010173689574,
        "q2_loss": 50.79085690081119,
        "policy_loss": 2.5547169232182205,
        "alpha_loss": 0.0,
        "total_reward": -42.290367602993875,
        "touch": 1,
        "won": 0,
        "lost": 1,
        "total_steps": 2078,
        "grad_updates": 1600
    },
    {
        "episode": 60,
        "q1_loss": 1.2552785416288923,
        "q2_loss": 56.6176142141223,
        "policy_loss": 2.7224794590069603,
        "alpha_loss": 0.0,
        "total_reward": -32.15852312881353,
        "touch": 1,
        "won": 0,
        "lost": 0,
        "total_steps": 2547,
        "grad_updates": 1920
    },
    {
        "episode": 70,
        "q1_loss": 1.2736619839311711,
        "q2_loss": 61.44306194484234,
        "policy_loss": 2.8471261938634727,
        "alpha_loss": 0.0,
        "total_reward": 5.1929932908062435,
        "touch": 1,
        "won": 1,
        "lost": 0,
        "total_steps": 2822,
        "grad_updates": 2240
    },
    {
        "episode": 80,
        "q1_loss": 1.2898151036933996,
        "q2_loss": 65.32776896096766,
        "policy_loss": 2.9492717765155247,
        "alpha_loss": 0.0,
        "total_reward": -66.00592339115363,
        "touch": 0,
        "won": 0,
        "lost": 1,
        "total_steps": 3448,
        "grad_updates": 2560
    },
    {
        "episode": 90,
        "q1_loss": 1.3144659434859123,
        "q2_loss": 68.32264575064183,
        "policy_loss": 3.0203449382446705,
        "alpha_loss": 0.0,
        "total_reward": -23.481617122376903,
        "touch": 0,
        "won": 0,
        "lost": 1,
        "total_steps": 3925,
        "grad_updates": 2880
    },
    {
        "episode": 100,
        "q1_loss": 1.3255871985759586,
        "q2_loss": 70.75548019438982,
        "policy_loss": 3.073212909689173,
        "alpha_loss": 0.0,
        "total_reward": -22.40102300113859,
        "touch": 0,
        "won": 0,
        "lost": 1,
        "total_steps": 4230,
        "grad_updates": 3200
    },
    {
        "episode": 110,
        "q1_loss": 1.3142965602011165,
        "q2_loss": 72.61928063007919,
        "policy_loss": 3.1109691701744766,
        "alpha_loss": 0.0,
        "total_reward": -59.230743528688905,
        "touch": 1,
        "won": 0,
        "lost": 0,
        "total_steps": 4540,
        "grad_updates": 3520
    },
    {
        "episode": 120,
        "q1_loss": 1.3010998932256674,
        "q2_loss": 74.04068743611376,
        "policy_loss": 3.1378903943657255,
        "alpha_loss": 0.0,
        "total_reward": -25.228049011796468,
        "touch": 0,
        "won": 0,
        "lost": 1,
        "total_steps": 4776,
        "grad_updates": 3840
    },
    {
        "episode": 130,
        "q1_loss": 1.308025659642254,
        "q2_loss": 75.07609287981803,
        "policy_loss": 3.1585695573845163,
        "alpha_loss": 0.0,
        "total_reward": -25.72168870439803,
        "touch": 0,
        "won": 0,
        "lost": 1,
        "total_steps": 5372,
        "grad_updates": 4160
    },
    {
        "episode": 140,
        "q1_loss": 1.3166538475280893,
        "q2_loss": 75.83879584691354,
        "policy_loss": 3.17667515764146,
        "alpha_loss": 0.0,
        "total_reward": -44.625801021813565,
        "touch": 1,
        "won": 0,
        "lost": 0,
        "total_steps": 5803,
        "grad_updates": 4480
    },
    {
        "episode": 150,
        "q1_loss": 1.3230505358614026,
        "q2_loss": 76.60165744403999,
        "policy_loss": 3.199549491821478,
        "alpha_loss": 0.0,
        "total_reward": -25.633543019246865,
        "touch": 0,
        "won": 0,
        "lost": 1,
        "total_steps": 6116,
        "grad_updates": 4800
    },
    {
        "episode": 160,
        "q1_loss": 1.3299195642175619,
        "q2_loss": 77.39187561813742,
        "policy_loss": 3.224640677700518,
        "alpha_loss": 0.0,
        "total_reward": -33.39262720322013,
        "touch": 1,
        "won": 0,
        "lost": 1,
        "total_steps": 6509,
        "grad_updates": 5120
    },
    {
        "episode": 170,
        "q1_loss": 1.3364914916948798,
        "q2_loss": 78.12173765915281,
        "policy_loss": 3.247883908379385,
        "alpha_loss": 0.0,
        "total_reward": -27.805470093144347,
        "touch": 0,
        "won": 0,
        "lost": 1,
        "total_steps": 6810,
        "grad_updates": 5440
    },
    {
        "episode": 180,
        "q1_loss": 1.34483999319685,
        "q2_loss": 78.8163043692708,
        "policy_loss": 3.272154146572575,
        "alpha_loss": 0.0,
        "total_reward": -43.62300396716425,
        "touch": 1,
        "won": 0,
        "lost": 1,
        "total_steps": 7196,
        "grad_updates": 5760
    },
    {
        "episode": 190,
        "q1_loss": 1.349280012707765,
        "q2_loss": 79.47884631172607,
        "policy_loss": 3.2963521298364196,
        "alpha_loss": 0.0,
        "total_reward": -24.999503448372216,
        "touch": 0,
        "won": 0,
        "lost": 1,
        "total_steps": 7710,
        "grad_updates": 6080
    },
    {
        "episode": 200,
        "q1_loss": 1.3608895598771051,
        "q2_loss": 79.99888648822903,
        "policy_loss": 3.318797719455324,
        "alpha_loss": 0.0,
        "total_reward": -46.84116550309403,
        "touch": 1,
        "won": 0,
        "lost": 0,
        "total_steps": 8130,
        "grad_updates": 6400
    },
    {
        "episode": 210,
        "q1_loss": 1.3691955287142523,
        "q2_loss": 80.42424406338306,
        "policy_loss": 3.335972477402538,
        "alpha_loss": 0.0,
        "total_reward": -0.12865063809078414,
        "touch": 1,
        "won": 1,
        "lost": 0,
        "total_steps": 8613,
        "grad_updates": 6720
    },
    {
        "episode": 220,
        "q1_loss": 1.3803150657352738,
        "q2_loss": 80.69854846881195,
        "policy_loss": 3.3503340614578603,
        "alpha_loss": 0.0,
        "total_reward": -21.42250513922678,
        "touch": 0,
        "won": 0,
        "lost": 1,
        "total_steps": 9130,
        "grad_updates": 7040
    },
    {
        "episode": 230,
        "q1_loss": 1.392382239068494,
        "q2_loss": 80.91003537294657,
        "policy_loss": 3.362665679836241,
        "alpha_loss": 0.0,
        "total_reward": -36.796367554611216,
        "touch": 1,
        "won": 0,
        "lost": 0,
        "total_steps": 9607,
        "grad_updates": 7360
    },
    {
        "episode": 240,
        "q1_loss": 1.404859587321213,
        "q2_loss": 81.00930294903615,
        "policy_loss": 3.370438259432558,
        "alpha_loss": 0.0,
        "total_reward": -117.57105432157934,
        "touch": 1,
        "won": 0,
        "lost": 1,
        "total_steps": 10029,
        "grad_updates": 7680
    },
    {
        "episode": 250,
        "q1_loss": 1.4113998294882477,
        "q2_loss": 80.93590221035481,
        "policy_loss": 3.3719073262177406,
        "alpha_loss": 0.0,
        "total_reward": -14.054341222624412,
        "touch": 1,
        "won": 0,
        "lost": 0,
        "total_steps": 10533,
        "grad_updates": 8000
    },
    {
        "episode": 260,
        "q1_loss": 1.418551855530733,
        "q2_loss": 80.80760108564908,
        "policy_loss": 3.3709312668034377,
        "alpha_loss": 0.0,
        "total_reward": -13.701139550305022,
        "touch": 1,
        "won": 0,
        "lost": 0,
        "total_steps": 10997,
        "grad_updates": 8320
    },
    {
        "episode": 270,
        "q1_loss": 1.423725820446594,
        "q2_loss": 80.72057352606897,
        "policy_loss": 3.3702447242586424,
        "alpha_loss": 0.0,
        "total_reward": -24.968322738698653,
        "touch": 0,
        "won": 0,
        "lost": 1,
        "total_steps": 11356,
        "grad_updates": 8640
    },
    {
        "episode": 280,
        "q1_loss": 1.4269938074085595,
        "q2_loss": 80.69730813003012,
        "policy_loss": 3.3716950323532466,
        "alpha_loss": 0.0,
        "total_reward": -23.24344319443617,
        "touch": 0,
        "won": 0,
        "lost": 1,
        "total_steps": 11864,
        "grad_updates": 8960
    },
    {
        "episode": 290,
        "q1_loss": 1.4337174035769342,
        "q2_loss": 80.6831333395736,
        "policy_loss": 3.372751593586571,
        "alpha_loss": 0.0,
        "total_reward": 2.742558799126959,
        "touch": 1,
        "won": 1,
        "lost": 0,
        "total_steps": 12300,
        "grad_updates": 9280
    },
    {
        "episode": 300,
        "q1_loss": 1.4390781815877804,
        "q2_loss": 80.63036569247643,
        "policy_loss": 3.3729936007627597,
        "alpha_loss": 0.0,
        "total_reward": -13.495473614144053,
        "touch": 1,
        "won": 1,
        "lost": 0,
        "total_steps": 12767,
        "grad_updates": 9600
    },
    {
        "episode": 310,
        "q1_loss": 1.442375639708893,
        "q2_loss": 80.69734430514997,
        "policy_loss": 3.376801514586494,
        "alpha_loss": 0.0,
        "total_reward": -65.99823783952668,
        "touch": 1,
        "won": 0,
        "lost": 1,
        "total_steps": 13158,
        "grad_updates": 9920
    },
    {
        "episode": 320,
        "q1_loss": 1.4481418595270952,
        "q2_loss": 80.77247081147507,
        "policy_loss": 3.3789001078082945,
        "alpha_loss": 0.0,
        "total_reward": -67.76778713250562,
        "touch": 1,
        "won": 0,
        "lost": 1,
        "total_steps": 13764,
        "grad_updates": 10240
    },
    {
        "episode": 330,
        "q1_loss": 1.455345438621148,
        "q2_loss": 80.90457383403272,
        "policy_loss": 3.383506183052492,
        "alpha_loss": 0.0,
        "total_reward": -61.80146825787509,
        "touch": 1,
        "won": 0,
        "lost": 1,
        "total_steps": 14295,
        "grad_updates": 10560
    },
    {
        "episode": 340,
        "q1_loss": 1.4650355381151552,
        "q2_loss": 81.03560410326018,
        "policy_loss": 3.386705354017699,
        "alpha_loss": 0.0,
        "total_reward": -51.90746544302727,
        "touch": 1,
        "won": 0,
        "lost": 1,
        "total_steps": 14781,
        "grad_updates": 10880
    },
    {
        "episode": 350,
        "q1_loss": 1.4726058653396155,
        "q2_loss": 81.15241777973516,
        "policy_loss": 3.389605307459299,
        "alpha_loss": 0.0,
        "total_reward": -40.71178761252545,
        "touch": 1,
        "won": 0,
        "lost": 0,
        "total_steps": 15360,
        "grad_updates": 11200
    },
    {
        "episode": 360,
        "q1_loss": 1.481409260798763,
        "q2_loss": 81.24175318984521,
        "policy_loss": 3.3912245795829223,
        "alpha_loss": 0.0,
        "total_reward": 1.542609250649189,
        "touch": 1,
        "won": 1,
        "lost": 0,
        "total_steps": 15890,
        "grad_updates": 11520
    },
    {
        "episode": 370,
        "q1_loss": 1.4871097614611122,
        "q2_loss": 81.30251599139459,
        "policy_loss": 3.3921729739830906,
        "alpha_loss": 0.0,
        "total_reward": 3.3998059783476915,
        "touch": 1,
        "won": 1,
        "lost": 0,
        "total_steps": 16421,
        "grad_updates": 11840
    },
    {
        "episode": 380,
        "q1_loss": 1.491645478562599,
        "q2_loss": 81.32781413613182,
        "policy_loss": 3.391684554583442,
        "alpha_loss": 0.0,
        "total_reward": 4.291292972641804,
        "touch": 1,
        "won": 1,
        "lost": 0,
        "total_steps": 16831,
        "grad_updates": 12160
    },
    {
        "episode": 390,
        "q1_loss": 1.4964544209126287,
        "q2_loss": 81.34580173805738,
        "policy_loss": 3.3909446981448967,
        "alpha_loss": 0.0,
        "total_reward": -26.975358063613548,
        "touch": 0,
        "won": 0,
        "lost": 1,
        "total_steps": 17437,
        "grad_updates": 12480
    },
    {
        "episode": 400,
        "q1_loss": 1.4996174294850788,
        "q2_loss": 81.34823626734317,
        "policy_loss": 3.3890924936695956,
        "alpha_loss": 0.0,
        "total_reward": -55.88696963049569,
        "touch": 1,
        "won": 0,
        "lost": 0,
        "total_steps": 18008,
        "grad_updates": 12800
    },
    {
        "episode": 410,
        "q1_loss": 1.5034395892468349,
        "q2_loss": 81.3474048493112,
        "policy_loss": 3.3868760918585084,
        "alpha_loss": 0.0,
        "total_reward": -26.456295722639098,
        "touch": 1,
        "won": 0,
        "lost": 0,
        "total_steps": 18632,
        "grad_updates": 13120
    },
    {
        "episode": 420,
        "q1_loss": 1.5092834864055649,
        "q2_loss": 81.35370230029027,
        "policy_loss": 3.3847755369929864,
        "alpha_loss": 0.0,
        "total_reward": -33.27677795832564,
        "touch": 1,
        "won": 0,
        "lost": 0,
        "total_steps": 19249,
        "grad_updates": 13440
    },
    {
        "episode": 430,
        "q1_loss": 1.51278749200797,
        "q2_loss": 81.36328150872575,
        "policy_loss": 3.382197594839733,
        "alpha_loss": 0.0,
        "total_reward": -39.01150333575458,
        "touch": 1,
        "won": 0,
        "lost": 0,
        "total_steps": 19783,
        "grad_updates": 13760
    },
    {
        "episode": 440,
        "q1_loss": 1.5150235006014223,
        "q2_loss": 81.39929662814194,
        "policy_loss": 3.3803865608399395,
        "alpha_loss": 0.0,
        "total_reward": -26.496731927109884,
        "touch": 0,
        "won": 0,
        "lost": 1,
        "total_steps": 20226,
        "grad_updates": 14080
    },
    {
        "episode": 450,
        "q1_loss": 1.5169122129119932,
        "q2_loss": 81.37629755530092,
        "policy_loss": 3.376368719064113,
        "alpha_loss": 0.0,
        "total_reward": -63.204300831965426,
        "touch": 1,
        "won": 0,
        "lost": 1,
        "total_steps": 20740,
        "grad_updates": 14400
    },
    {
        "episode": 460,
        "q1_loss": 1.5178191017987126,
        "q2_loss": 81.28905145273261,
        "policy_loss": 3.3714475517910296,
        "alpha_loss": 0.0,
        "total_reward": 2.4302354696664095,
        "touch": 1,
        "won": 1,
        "lost": 0,
        "total_steps": 21209,
        "grad_updates": 14720
    },
    {
        "episode": 470,
        "q1_loss": 1.5196257569747877,
        "q2_loss": 81.17883378806266,
        "policy_loss": 3.365907703227106,
        "alpha_loss": 0.0,
        "total_reward": -2.5235697206102774,
        "touch": 1,
        "won": 1,
        "lost": 0,
        "total_steps": 21791,
        "grad_updates": 15040
    },
    {
        "episode": 480,
        "q1_loss": 1.520878091386597,
        "q2_loss": 81.04780332675824,
        "policy_loss": 3.3585798939903424,
        "alpha_loss": 0.0,
        "total_reward": -23.750450682610072,
        "touch": 0,
        "won": 0,
        "lost": 1,
        "total_steps": 22286,
        "grad_updates": 15360
    },
    {
        "episode": 490,
        "q1_loss": 1.5220436043524164,
        "q2_loss": 80.92002594987957,
        "policy_loss": 3.352341084134746,
        "alpha_loss": 0.0,
        "total_reward": -63.543849558682496,
        "touch": 0,
        "won": 0,
        "lost": 1,
        "total_steps": 22935,
        "grad_updates": 15680
    },
    {
        "episode": 500,
        "q1_loss": 1.5209154051151126,
        "q2_loss": 80.72930900079012,
        "policy_loss": 3.344081819726154,
        "alpha_loss": 0.0,
        "total_reward": -2.1309521596548233,
        "touch": 1,
        "won": 1,
        "lost": 0,
        "total_steps": 23510,
        "grad_updates": 16000
    },
    {
        "episode": 510,
        "q1_loss": 1.5209377273168487,
        "q2_loss": 80.57138079995033,
        "policy_loss": 3.3365303565967173,
        "alpha_loss": 0.0,
        "total_reward": -23.97521754965598,
        "touch": 0,
        "won": 0,
        "lost": 1,
        "total_steps": 24017,
        "grad_updates": 16320
    },
    {
        "episode": 520,
        "q1_loss": 1.5215359963136368,
        "q2_loss": 80.42311673330573,
        "policy_loss": 3.329999247427958,
        "alpha_loss": 0.0,
        "total_reward": -48.89099090442338,
        "touch": 1,
        "won": 0,
        "lost": 0,
        "total_steps": 24596,
        "grad_updates": 16640
    },
    {
        "episode": 530,
        "q1_loss": 1.5220161477015968,
        "q2_loss": 80.24808101524722,
        "policy_loss": 3.32279016112487,
        "alpha_loss": 0.0,
        "total_reward": -35.397641821646296,
        "touch": 1,
        "won": 0,
        "lost": 0,
        "total_steps": 24988,
        "grad_updates": 16960
    },
    {
        "episode": 540,
        "q1_loss": 1.5230879769401833,
        "q2_loss": 80.09741854209591,
        "policy_loss": 3.315606640394846,
        "alpha_loss": 0.0,
        "total_reward": -29.913427420581073,
        "touch": 1,
        "won": 0,
        "lost": 0,
        "total_steps": 25630,
        "grad_updates": 17280
    },
    {
        "episode": 550,
        "q1_loss": 1.5225303845971145,
        "q2_loss": 79.93966305629773,
        "policy_loss": 3.308419235218316,
        "alpha_loss": 0.0,
        "total_reward": -13.933262460608084,
        "touch": 1,
        "won": 1,
        "lost": 0,
        "total_steps": 26170,
        "grad_updates": 17600
    },
    {
        "episode": 560,
        "q1_loss": 1.5239411427423224,
        "q2_loss": 79.77977626201297,
        "policy_loss": 3.3017745028965044,
        "alpha_loss": 0.0,
        "total_reward": -37.805906715444294,
        "touch": 0,
        "won": 0,
        "lost": 1,
        "total_steps": 26736,
        "grad_updates": 17920
    },
    {
        "episode": 570,
        "q1_loss": 1.524278087069264,
        "q2_loss": 79.6118325347963,
        "policy_loss": 3.294278267893548,
        "alpha_loss": 0.0,
        "total_reward": -24.08616027195705,
        "touch": 1,
        "won": 1,
        "lost": 0,
        "total_steps": 27281,
        "grad_updates": 18240
    },
    {
        "episode": 580,
        "q1_loss": 1.5250485296088174,
        "q2_loss": 79.45044614667522,
        "policy_loss": 3.286952045609661,
        "alpha_loss": 0.0,
        "total_reward": -22.7293282378632,
        "touch": 0,
        "won": 0,
        "lost": 1,
        "total_steps": 27726,
        "grad_updates": 18560
    },
    {
        "episode": 590,
        "q1_loss": 1.5253350685129605,
        "q2_loss": 79.28648916881973,
        "policy_loss": 3.2797857341356575,
        "alpha_loss": 0.0,
        "total_reward": -33.07330201714062,
        "touch": 1,
        "won": 0,
        "lost": 0,
        "total_steps": 28342,
        "grad_updates": 18880
    }
]